CHANGELOG.md
README.md
pytest_alembic/__init__.py
pytest_alembic/config.py
pytest_alembic/executor.py
pytest_alembic/history.py
pytest_alembic/plugin/__init__.py
pytest_alembic/plugin/error.py
pytest_alembic/plugin/fixtures.py
pytest_alembic/plugin/hooks.py
pytest_alembic/plugin/plugin.py
pytest_alembic/py.typed
pytest_alembic/revision_data.py
pytest_alembic/runner.py
pytest_alembic/tests/__init__.py
pytest_alembic/tests/default.py
pytest_alembic/tests/experimental/__init__.py
pytest_alembic/tests/experimental/all_models_register_on_metadata.py
pytest_alembic/tests/experimental/collect_clean_alembic_environment.py
pytest_alembic/tests/experimental/downgrade_leaves_no_trace.py
pytest_alembic-0.12.0.dist-info/entry_points.txt
pytest_alembic-0.12.0.dist-info/LICENSE
pytest_alembic-0.12.0.dist-info/WHEEL
pytest_alembic-0.12.0.dist-info/METADATA
pytest_alembic-0.12.0.dist-info/RECORD
